ojota/__init__.py
ojota/base.py
ojota/cache.py
ojota/sources.py
ojota-3.3.1.dist-info/licenses/LICENSE.txt
ojota-3.3.1.dist-info/METADATA
ojota-3.3.1.dist-info/WHEEL
ojota-3.3.1.dist-info/top_level.txt
ojota-3.3.1.dist-info/RECORD
