Metadata-Version: 2.4
Name: Ojota
Version: 3.3.1
Summary: Flat File Database with ORM
Home-page: http://pypi.python.org/pypi/Ojota/
Author: Luis Andres Giordano
Author-email: agiordano@msa.com.ar
License: LICENSE.txt
License-File: LICENSE.txt
Requires-Dist: six
Dynamic: author
Dynamic: author-email
Dynamic: description
Dynamic: home-page
Dynamic: license
Dynamic: license-file
Dynamic: requires-dist
Dynamic: summary
